MANIFEST.in
README.rst
setup.py
docs/.HISTORY.rst.un~
docs/HISTORY.rst
xuru/__init__.py
xuru.recipe.android.egg-info/PKG-INFO
xuru.recipe.android.egg-info/SOURCES.txt
xuru.recipe.android.egg-info/dependency_links.txt
xuru.recipe.android.egg-info/entry_points.txt
xuru.recipe.android.egg-info/namespace_packages.txt
xuru.recipe.android.egg-info/requires.txt
xuru.recipe.android.egg-info/top_level.txt
xuru.recipe.android.egg-info/zip-safe
xuru/recipe/__init__.py
xuru/recipe/android/__init__.py
xuru/recipe/android/android.py