Metadata-Version: 1.0
Name: xuru.recipe.android
Version: 0.10.0
Summary: A zc.buildout recipe that will install the android sdk and install tools, apis, and images
Home-page: https://github.com/xuru/xuru.recipe.android
Author: Eric Plaster
Author-email: plaster@gmail.com
License: MIT License
Keywords: android buildout
Platform: UNKNOWN
Classifier: Framework :: Buildout
Classifier: Development Status :: 4 - Beta
Classifier: Intended Audience :: Developers
Classifier: License :: OSI Approved :: MIT License
Classifier: Topic :: Software Development :: Build Tools
Classifier: Topic :: Software Development :: Libraries :: Python Modules
